pytholog/__init__.py
pytholog/expr.py
pytholog/fact.py
pytholog/goal.py
pytholog/knowledge_base.py
pytholog/pq.py
pytholog/querizer.py
pytholog/search_util.py
pytholog/unify.py
pytholog/util.py
pytholog-2.4.1.dist-info/LICENSE
pytholog-2.4.1.dist-info/METADATA
pytholog-2.4.1.dist-info/WHEEL
pytholog-2.4.1.dist-info/top_level.txt
pytholog-2.4.1.dist-info/RECORD
