Metadata-Version: 2.1
Name: pytholog
Version: 2.4.1
Summary: Logic Programming in Python
Home-page: https://github.com/mnoorfawi/pytholog
Author: Muhammad N. Fawi
Author-email: m.noor.fawi@gmail.com
License: MIT
Platform: UNKNOWN
Classifier: License :: OSI Approved :: MIT License
Classifier: Programming Language :: Python :: 3
Classifier: Programming Language :: Python :: 3.7
Requires-Dist: more-itertools
